{
  "config": {
    "pantalla": "5"
  },
  "default": "https://project-cast.sfo3.cdn.digitaloceanspaces.com/pantalla5/p5_nacional.mp4",
  "perfiles": {
    "chiltiupan": "https://project-cast.sfo3.cdn.digitaloceanspaces.com/pantalla5/p5_perfilA.mp4",
    "valledulce": "https://project-cast.sfo3.cdn.digitaloceanspaces.com/pantalla5/p5_perfilB.mp4",
    "zarzamora": "https://project-cast.sfo3.cdn.digitaloceanspaces.com/pantalla5/p5_perfilB.mp4",
    "lasramblas": "https://project-cast.sfo3.cdn.digitaloceanspaces.com/pantalla5/p5_perfilB.mp4",
    "bambu": "https://project-cast.sfo3.cdn.digitaloceanspaces.com/pantalla5/p5_perfilC.mp4"
  }
}
